sequential_circuit/RAM/syn_FIFO.v
module syn_FIFO(
    input clk,
    input reset,
    input wr_enb,
    input rd_enb,
    input [7:0] din,
    output reg [7:0] dout,
    output full,
    output empty
);

reg [7:0] mem [7:0];
reg [3:0] wr_ptr;
reg [3:0] rd_ptr;
integer i;

assign empty = (wr_ptr == rd_ptr);

assign full = (wr_ptr[3] != rd_ptr[3]) &&
              (wr_ptr[2:0] == rd_ptr[2:0]);

always @(posedge clk) begin
    if (reset) begin
        wr_ptr <= 4'b0;
        rd_ptr <= 4'b0;
        dout <= 8'b0;

        for (i = 0; i < 8; i = i + 1)
            mem[i] <= 8'b0;
    end
    else begin

        if (wr_enb && !full) begin
            mem[wr_ptr[2:0]] <= din;
            wr_ptr <= wr_ptr + 1'b1;
        end

        if (rd_enb && !empty) begin
            dout <= mem[rd_ptr[2:0]];
            rd_ptr <= rd_ptr + 1'b1;
        end

    end
end

endmodule

sequential_circuit/RAM/syn_FIFO_tb.v
`timescale 1ns/1ps

module syn_FIFO_tb;

reg clk;
reg reset;
reg wr_enb;
reg rd_enb;
reg [7:0] din;

wire [7:0] dout;
wire full;
wire empty;

syn_FIFO dut (
    .clk(clk),
    .reset(reset),
    .wr_enb(wr_enb),
    .rd_enb(rd_enb),
    .din(din),
    .dout(dout),
    .full(full),
    .empty(empty)
);

always #5 clk = ~clk;

initial begin
    clk = 0;
    reset = 1;
    wr_enb = 0;
    rd_enb = 0;
    din = 8'h00;

    #10;
    reset = 0;

    // Write data
    wr_enb = 1;

    din = 8'h11;
    #10;

    din = 8'h22;
    #10;

    din = 8'h33;
    #10;

    din = 8'h44;
    #10;

    din = 8'h55;
    #10;

    din = 8'h66;
    #10;

    din = 8'h77;
    #10;

    din = 8'h88;
    #10;

    wr_enb = 0;

    // Read data
    rd_enb = 1;

    #10;
    #10;
    #10;
    #10;
    #10;
    #10;
    #10;
    #10;

    rd_enb = 0;

    #10;

    $finish;
end

initial begin
    $monitor("TIME=%0t |CLK=%b | RESET=%b | WR=%b | RD=%b | DIN=%h | DOUT=%h | FULL=%b | EMPTY=%b",
             $time,clk, reset, wr_enb, rd_enb, din, dout, full, empty);
end

initial begin
    $dumpfile("syn_FIFO.vcd");
    $dumpvars(0, syn_FIFO_tb);
end

endmodule

sequential_circuit/RAM/syn_FIFO.vcd
$date
	Wed Sep  2 07:37:25 2026
$end
$version
	Icarus Verilog
$end
$timescale
	1ps
$end
$scope module syn_FIFO_tb $end
$var wire 1 ! full $end
$var wire 1 " empty $end
$var wire 8 # dout [7:0] $end
$var reg 1 $ clk $end
$var reg 8 % din [7:0] $end
$var reg 1 & rd_enb $end
$var reg 1 ' reset $end
$var reg 1 ( wr_enb $end
$scope module dut $end
$var wire 1 $ clk $end
$var wire 8 ) din [7:0] $end
$var wire 1 ! full $end
$var wire 1 & rd_enb $end
$var wire 1 ' reset $end
$var wire 1 ( wr_enb $end
$var wire 1 " empty $end
$var reg 8 * dout [7:0] $end
$var reg 4 + rd_ptr [3:0] $end
$var reg 4 , wr_ptr [3:0] $end
$var integer 32 - i [31:0] $end
$upscope $end
$upscope $end
$enddefinitions $end
$comment Show the parameter values. $end
$dumpall
$end
#0
$dumpvars
bx -
bx ,
bx +
bx *
b0 )
0(
1'
0&
b0 %
0$
bx #
x"
x!
$end
#5000
0!
b0 #
b0 *
1"
b0 +
b0 ,
b1000 -
1$
#10000
0$
b10001 %
b10001 )
1(
0'
#15000
0"
b1 ,
1$
#20000
0$
b100010 %
b100010 )
#25000
b10 ,
1$
#30000
0$
b110011 %
b110011 )
#35000
b11 ,
1$
#40000
0$
b1000100 %
b1000100 )
#45000
b100 ,
1$
#50000
0$
b1010101 %
b1010101 )
#55000
b101 ,
1$
#60000
0$
b1100110 %
b1100110 )
#65000
b110 ,
1$
#70000
0$
b1110111 %
b1110111 )
#75000
b111 ,
1$
#80000
0$
b10001000 %
b10001000 )
#85000
1!
b1000 ,
1$
#90000
0$
1&
0(
#95000
0!
b1 +
b10001 #
b10001 *
1$
#100000
0$
#105000
b10 +
b100010 #
b100010 *
1$
#110000
0$
#115000
b11 +
b110011 #
b110011 *
1$
#120000
0$
#125000
b100 +
b1000100 #
b1000100 *
1$
#130000
0$
#135000
b101 +
b1010101 #
b1010101 *
1$
#140000
0$
#145000
b110 +
b1100110 #
b1100110 *
1$
#150000
0$
#155000
b111 +
b1110111 #
b1110111 *
1$
#160000
0$
#165000
0!
1"
b1000 +
b10001000 #
b10001000 *
1$
#170000
0$
0&
