practice_question/ram_16to16.v
module ram_16to16 (
input clk,rst,wr_en,rd_en,
input [3:0]addr,
input [15:0]din,
output reg [15:0]dout
);
reg[15:0]mem[15:0];
integer i;
always@(posedge clk)begin
	if(rst)begin
		for(i=0;i<16;i=i+1)
			mem[i]<=0;
		dout<=0;
	end
	else if(wr_en==1)
		mem[addr]<=din;
	else if(rd_en==1)
		dout<=mem[addr];
end
endmodule

practice_question/ram_16to16_tb.v
module ram_16to16_tb;
reg clk,rst,wr_en,rd_en;
reg [3:0] addr;
reg [15:0] din;
wire [15:0] dout;
ram_16to16 RAM(
	.clk(clk),
	.rst(rst),
	.wr_en(wr_en),
	.rd_en(rd_en),
	.addr(addr),
	.din(din),
	.dout(dout)
);

always #5 clk=~clk;

initial begin
	clk=0;
	rst=1;
	wr_en=0;
	rd_en=0;
	din=0;

	#10 rst=0;


	//write operation
	
	#10 wr_en=1;
	addr=4'd12;
	din=16'h128;


	#10 wr_en=0;
	addr=4'd12;


	#10 rd_en=1;
	addr=4'd12;

	#10 rd_en=0;



	#50;
	$finish;
end
initial begin
	$dumpfile("ram.vcd");
        $dumpvars(0,ram_16to16_tb);
end

initial begin
	$monitor("time=%0t clk=%b rst=%b wr_en=%b rd_en=%b addr=%b(%d) din=%b(%h) dout=%b(%h)",
		$time,clk,rst,wr_en,rd_en,addr,addr,din,din,dout,dout);
end
endmodule

practice_question/ram.vcd
$date
	Sat Oct 10 16:20:34 2026
$end
$version
	Icarus Verilog
$end
$timescale
	1s
$end
$scope module ram_16to16_tb $end
$var wire 16 ! dout [15:0] $end
$var reg 4 " addr [3:0] $end
$var reg 1 # clk $end
$var reg 16 $ din [15:0] $end
$var reg 1 % rd_en $end
$var reg 1 & rst $end
$var reg 1 ' wr_en $end
$scope module RAM $end
$var wire 4 ( addr [3:0] $end
$var wire 1 # clk $end
$var wire 16 ) din [15:0] $end
$var wire 1 % rd_en $end
$var wire 1 & rst $end
$var wire 1 ' wr_en $end
$var reg 16 * dout [15:0] $end
$var integer 32 + i [31:0] $end
$upscope $end
$upscope $end
$enddefinitions $end
$comment Show the parameter values. $end
$dumpall
$end
#0
$dumpvars
bx +
bx *
b0 )
bx (
0'
1&
0%
b0 $
0#
bx "
bx !
$end
#5
b0 !
b0 *
b10000 +
1#
#10
0#
0&
#15
1#
#20
0#
b100101000 $
b100101000 )
b1100 "
b1100 (
1'
#25
1#
#30
0#
0'
#35
1#
#40
0#
1%
#45
b100101000 !
b100101000 *
1#
#50
0#
0%
